gensay/__about__.py
gensay/__init__.py
gensay/cache.py
gensay/main.py
gensay/providers/__init__.py
gensay/providers/amazon_polly.py
gensay/providers/base.py
gensay/providers/chatterbox.py
gensay/providers/elevenlabs.py
gensay/providers/macos_say.py
gensay/providers/mock.py
gensay/providers/openai.py
gensay/text_chunker.py
gensay-0.4.2.dist-info/WHEEL
gensay-0.4.2.dist-info/entry_points.txt
gensay-0.4.2.dist-info/METADATA
gensay-0.4.2.dist-info/RECORD
