Metadata-Version: 2.4
Name: gensay
Version: 0.4.2
Summary: Multi-provider TTS tool compatible with macOS say command. Supports Chatterbox TTS for local; ElevenLabs, OpenAI, AWS Polly for cloud APIs
Keywords: 
Author: Anthony Wu
Author-email: Anthony Wu <pls-file-gh-issue@users.noreply.github.com>
License-Expression: MIT
Classifier: Development Status :: 3 - Alpha
Classifier: Programming Language :: Python
Classifier: Programming Language :: Python :: 3.11
Classifier: Programming Language :: Python :: 3.12
Classifier: Programming Language :: Python :: 3.13
Classifier: Programming Language :: Python :: Implementation :: CPython
Requires-Dist: boto3>=1.40.0,<2.0
Requires-Dist: botocore[crt]>=1.40.0,<2.0
Requires-Dist: diskcache>=5.6.3,<6.0
Requires-Dist: distro>=1.9.0,<2.0
Requires-Dist: hf-transfer>=0.1.9,<1.0
Requires-Dist: openai>=1.98.0,<2.0
Requires-Dist: platformdirs>=4.3,<5.0
Requires-Dist: psutil>=7.0,<8.0
Requires-Dist: python-dotenv>=1.1.1,<2.0
Requires-Dist: tqdm>=4.67,<5.0
Requires-Dist: gensay[audio-formats,chatterbox,elevenlabs] ; extra == 'all'
Requires-Dist: pydub>=0.25.0 ; extra == 'audio-formats'
Requires-Dist: ffmpeg-python>=0.2.0 ; extra == 'audio-formats'
Requires-Dist: accelerate>=1.9.0 ; extra == 'chatterbox'
Requires-Dist: audioop-lts>=0.2.2,<1.0 ; python_full_version >= '3.13' and extra == 'chatterbox'
Requires-Dist: diffusers>=0.34.0 ; extra == 'chatterbox'
Requires-Dist: numba>=0.60.0 ; extra == 'chatterbox'
Requires-Dist: numpy>=1.26.0 ; extra == 'chatterbox'
Requires-Dist: peft>=0.16.0,<1.0 ; extra == 'chatterbox'
Requires-Dist: pydub>=0.25,<1.0 ; extra == 'chatterbox'
Requires-Dist: torch>=2.6,<3.0 ; extra == 'chatterbox'
Requires-Dist: torchaudio>=2.6,<3.0 ; extra == 'chatterbox'
Requires-Dist: elevenlabs[pyaudio]>=2.0,<3.0 ; extra == 'elevenlabs'
Requires-Python: >=3.11
Project-URL: Documentation, https://github.com/anthonywu/gensay#readme
Project-URL: Issues, https://github.com/anthonywu/gensay/issues
Project-URL: Source, https://github.com/anthonywu/gensay
Provides-Extra: all
Provides-Extra: audio-formats
Provides-Extra: chatterbox
Provides-Extra: elevenlabs
